litemem/__init__.py
litemem/mem.py
litemem/model_path.py
litemem/models/all-MiniLM-L6-v2-Q8_0.gguf
litemem-0.1.3.dist-info/licenses/LICENSE
litemem-0.1.3.dist-info/METADATA
litemem-0.1.3.dist-info/WHEEL
litemem-0.1.3.dist-info/top_level.txt
litemem-0.1.3.dist-info/RECORD
