Metadata-Version: 2.4
Name: litemem
Version: 0.1.3
Summary: Lightweight memory store for embeddings
Author: Ivan
License: MIT
Classifier: License :: OSI Approved :: MIT License
Classifier: Programming Language :: Python :: 3
Classifier: Programming Language :: Python :: 3.12
Classifier: Operating System :: OS Independent
Classifier: Topic :: Software Development :: Libraries
Requires-Python: >=3.12
License-File: LICENSE
Requires-Dist: sqlite-lembed>=0.0.1a8
Requires-Dist: sqlite-vec>=0.1.6
Dynamic: license-file
